leaptable/__init__.py
leaptable/agents/browser/Dockerfile
leaptable/agents/browser/__init__.py
leaptable/agents/browser/main.py
leaptable/agents/jungle/README.md
leaptable/agents/serp/Dockerfile
leaptable/agents/serp/__init__.py
leaptable/agents/serp/main.py
leaptable/client/__init__.py
leaptable/client/grpc/__init__.py
leaptable/client/grpc/collections.proto
leaptable/client/grpc/collections_service.proto
leaptable/client/grpc/json_with_int.proto
leaptable/client/grpc/nnext.proto
leaptable/client/grpc/points.proto
leaptable/client/grpc/points_service.proto
leaptable/client/grpc/snapshots_service.proto
leaptable/client/http/__init__.py
leaptable/client/http/api/__init__.py
leaptable/client/http/api/cluster_api.py
leaptable/client/http/api/collections_api.py
leaptable/client/http/api/default_api.py
leaptable/client/http/api/points_api.py
leaptable/client/http/api/snapshots_api.py
leaptable/client/http/api_client.py
leaptable/client/http/configuration.py
leaptable/client/http/exceptions.py
leaptable/client/http/models/__init__.py
leaptable/client/http/models/models.py
leaptable/client/nnext_client.py
leaptable/client/uploader/__init__.py
leaptable/client/uploader/grpc_uploader.py
leaptable/client/uploader/rest_uploader.py
leaptable/client/uploader/uploader.py
leaptable/conversions/__init__.py
leaptable/conversions/common_types.py
leaptable/conversions/conversion.py
leaptable/dataframe/__init__.py
leaptable/lib/__init__.py
leaptable/lib/core/StreamProcessor.py
leaptable/lib/core/__init__.py
leaptable/lib/core/decor.py
leaptable/lib/core/main.py
leaptable/lib/core/prompts.py
leaptable/lib/core/tool.py
leaptable/lib/models/__init__.py
leaptable/lib/models/chat/__init__.py
leaptable/lib/models/chat/openai_chat.py
leaptable/lib/models/llms/main.py
leaptable/lib/models/models.py
leaptable/lib/utils/__init__.py
leaptable/lib/utils/main.py
leaptable/lib/vectorstores/__init__.py
leaptable/lib/vectorstores/base.py
leaptable/lib/vectorstores/pinecone.py
leaptable-0.0.1.dist-info/LICENSE
leaptable-0.0.1.dist-info/METADATA
leaptable-0.0.1.dist-info/WHEEL
leaptable-0.0.1.dist-info/RECORD
